pymap3d/__init__.py
pymap3d/aer.py
pymap3d/azelradec.py
pymap3d/ecef.py
pymap3d/eci.py
pymap3d/ellipsoid.py
pymap3d/enu.py
pymap3d/haversine.py
pymap3d/latitude.py
pymap3d/los.py
pymap3d/lox.py
pymap3d/mathfun.py
pymap3d/ned.py
pymap3d/rcurve.py
pymap3d/rsphere.py
pymap3d/sidereal.py
pymap3d/spherical.py
pymap3d/timeconv.py
pymap3d/utils.py
pymap3d/vallado.py
pymap3d/vincenty.py
pymap3d/tests/__init__.py
pymap3d/tests/test_aer.py
pymap3d/tests/test_eci.py
pymap3d/tests/test_ellipsoid.py
pymap3d/tests/test_enu.py
pymap3d/tests/test_geodetic.py
pymap3d/tests/test_latitude.py
pymap3d/tests/test_look_spheroid.py
pymap3d/tests/test_ned.py
pymap3d/tests/test_pyproj.py
pymap3d/tests/test_rcurve.py
pymap3d/tests/test_rhumb.py
pymap3d/tests/test_rsphere.py
pymap3d/tests/test_sidereal.py
pymap3d/tests/test_sky.py
pymap3d/tests/test_spherical.py
pymap3d/tests/test_time.py
pymap3d/tests/test_vincenty.py
pymap3d/tests/test_vincenty_dist.py
pymap3d/tests/test_vincenty_vreckon.py
pymap3d-3.0.1.dist-info/LICENSE
pymap3d-3.0.1.dist-info/METADATA
pymap3d-3.0.1.dist-info/WHEEL
pymap3d-3.0.1.dist-info/top_level.txt
pymap3d-3.0.1.dist-info/RECORD
