Metadata-Version: 2.1
Name: pymap3d
Version: 3.0.1
Summary: pure Python (no prereqs) coordinate conversions, following convention of several popular Matlab routines.
Keywords: coordinate-conversion,geodesy
Classifier: Development Status :: 5 - Production/Stable
Classifier: Environment :: Console
Classifier: Intended Audience :: Science/Research
Classifier: License :: OSI Approved :: BSD License
Classifier: Operating System :: OS Independent
Classifier: Programming Language :: Python :: 3
Classifier: Topic :: Scientific/Engineering :: GIS
Requires-Python: >=3.8
Provides-Extra: tests
Provides-Extra: lint
Provides-Extra: coverage
Provides-Extra: format
Provides-Extra: core
Provides-Extra: full
Provides-Extra: proj
License-File: LICENSE
